heritage/__init__.py
heritage/cli.py
heritage/constants.py
heritage/heritage.py
heritage/models.py
heritage/utils.py
heritage-0.1.2.dist-info/licenses/AUTHORS.rst
heritage-0.1.2.dist-info/licenses/LICENSE
heritage-0.1.2.dist-info/METADATA
heritage-0.1.2.dist-info/WHEEL
heritage-0.1.2.dist-info/entry_points.txt
heritage-0.1.2.dist-info/top_level.txt
heritage-0.1.2.dist-info/RECORD
