Metadata-Version: 2.4
Name: heritage
Version: 0.1.2
Summary: Python Interface to The Sanskrit Heritage Site
Home-page: https://github.com/hrishikeshrt/heritage
Author: Hrishikesh Terdalkar
Author-email: hrishikeshrt@linuxmail.org
License: GNU General Public License v3
Keywords: heritage
Classifier: Development Status :: 2 - Pre-Alpha
Classifier: Intended Audience :: Developers
Classifier: License :: OSI Approved :: GNU General Public License v3 (GPLv3)
Classifier: Natural Language :: English
Classifier: Programming Language :: Python :: 3
Classifier: Programming Language :: Python :: 3.6
Classifier: Programming Language :: Python :: 3.7
Classifier: Programming Language :: Python :: 3.8
Classifier: Programming Language :: Python :: 3.9
Classifier: Programming Language :: Python :: 3.10
Requires-Python: >=3.6
License-File: LICENSE
License-File: AUTHORS.rst
Requires-Dist: requests>=2.26.0
Requires-Dist: beautifulsoup4>=4.10.0
Dynamic: author
Dynamic: author-email
Dynamic: classifier
Dynamic: description
Dynamic: home-page
Dynamic: keywords
Dynamic: license
Dynamic: license-file
Dynamic: requires-dist
Dynamic: requires-python
Dynamic: summary
